pipable/__init__.py
pipable-0.3.4.dist-info/LICENSE
pipable-0.3.4.dist-info/METADATA
pipable-0.3.4.dist-info/WHEEL
pipable-0.3.4.dist-info/RECORD
