Metadata-Version: 2.1
Name: pipable
Version: 0.3.4
Summary: pseudo pipe operation in python
Home-page: https://github.com/hoishing/pipable
License: MIT
Keywords: pipe,FP,functional programming,chain
Author: Kelvin Ng
Author-email: hoishing@gmail.com
Requires-Python: >=3.12,<4.0
Classifier: License :: OSI Approved :: MIT License
Classifier: Programming Language :: Python :: 3
Classifier: Programming Language :: Python :: 3.12
Project-URL: Documentation, https://hoishing.github.io/pipable
Project-URL: Repository, https://github.com/hoishing/pipable
